qinling/__init__.py
qinling/config.py
qinling/context.py
qinling/exceptions.py
qinling/rpc.py
qinling/status.py
qinling/version.py
qinling/api/__init__.py
qinling/api/access_control.py
qinling/api/app.py
qinling/api/service.py
qinling/api/wsgi.py
qinling/api/controllers/__init__.py
qinling/api/controllers/root.py
qinling/api/controllers/v1/__init__.py
qinling/api/controllers/v1/execution.py
qinling/api/controllers/v1/function.py
qinling/api/controllers/v1/function_alias.py
qinling/api/controllers/v1/function_version.py
qinling/api/controllers/v1/job.py
qinling/api/controllers/v1/resources.py
qinling/api/controllers/v1/root.py
qinling/api/controllers/v1/runtime.py
qinling/api/controllers/v1/types.py
qinling/api/controllers/v1/webhook.py
qinling/cmd/__init__.py
qinling/cmd/api.py
qinling/cmd/engine.py
qinling/cmd/status.py
qinling/db/__init__.py
qinling/db/api.py
qinling/db/base.py
qinling/db/sqlalchemy/__init__.py
qinling/db/sqlalchemy/api.py
qinling/db/sqlalchemy/filters.py
qinling/db/sqlalchemy/model_base.py
qinling/db/sqlalchemy/models.py
qinling/db/sqlalchemy/types.py
qinling/db/sqlalchemy/migration/__init__.py
qinling/db/sqlalchemy/migration/alembic.ini
qinling/db/sqlalchemy/migration/cli.py
qinling/db/sqlalchemy/migration/alembic_migrations/README.md
qinling/db/sqlalchemy/migration/alembic_migrations/__init__.py
qinling/db/sqlalchemy/migration/alembic_migrations/env.py
qinling/db/sqlalchemy/migration/alembic_migrations/script.py.mako
qinling/db/sqlalchemy/migration/alembic_migrations/versions/001_pike.py
qinling/db/sqlalchemy/migration/alembic_migrations/versions/002_add_function_version_support.py
qinling/db/sqlalchemy/migration/alembic_migrations/versions/003_add_cpu_column.py
qinling/db/sqlalchemy/migration/alembic_migrations/versions/004_add_function_aliases_support.py
qinling/db/sqlalchemy/migration/alembic_migrations/versions/005_add_trusted_for_runtime.py
qinling-5.0.0.dist-info/DESCRIPTION.rst
qinling-5.0.0.dist-info/METADATA
qinling-5.0.0.dist-info/RECORD
qinling-5.0.0.dist-info/WHEEL
qinling-5.0.0.dist-info/entry_points.txt
qinling-5.0.0.dist-info/metadata.json
qinling-5.0.0.dist-info/pbr.json
qinling-5.0.0.dist-info/top_level.txt
