Metadata-Version: 2.0
Name: qinling
Version: 5.0.0
Summary: Function as a Service
Home-page: https://docs.openstack.org/qinling/latest/
Author: OpenStack Qinling Team
Author-email: openstack-discuss@lists.openstack.org
License: UNKNOWN
Platform: UNKNOWN
Classifier: Environment :: OpenStack
Classifier: Intended Audience :: Information Technology
Classifier: Intended Audience :: System Administrators
Classifier: License :: OSI Approved :: Apache Software License
Classifier: Operating System :: POSIX :: Linux
Classifier: Programming Language :: Python
Classifier: Programming Language :: Python :: Implementation :: CPython
Classifier: Programming Language :: Python :: 3 :: Only
Classifier: Programming Language :: Python :: 3
Classifier: Programming Language :: Python :: 3.6
Classifier: Programming Language :: Python :: 3.7
Classifier: Programming Language :: Python :: 3.8
Requires-Python: >=3.6
Requires-Dist: Babel (!=2.4.0,>=2.3.4)
Requires-Dist: PyMySQL (>=0.7.6)
Requires-Dist: PyYAML (>=3.12)
Requires-Dist: SQLAlchemy (!=1.1.5,!=1.1.6,!=1.1.7,!=1.1.8,>=1.0.10)
Requires-Dist: WSME (>=0.8.0)
Requires-Dist: cotyledon (>=1.3.0)
Requires-Dist: croniter (>=0.3.4)
Requires-Dist: etcd3gw (>=0.2.3)
Requires-Dist: keystoneauth1 (>=3.4.0)
Requires-Dist: keystonemiddleware (>=4.17.0)
Requires-Dist: kubernetes (>=6.0.0)
Requires-Dist: oslo.concurrency (>=3.26.0)
Requires-Dist: oslo.config (>=5.2.0)
Requires-Dist: oslo.db (>=4.27.0)
Requires-Dist: oslo.log (>=3.36.0)
Requires-Dist: oslo.messaging (>=5.29.0)
Requires-Dist: oslo.middleware (>=3.35.0)
Requires-Dist: oslo.policy (>=1.30.0)
Requires-Dist: oslo.serialization (!=2.19.1,>=2.18.0)
Requires-Dist: oslo.service (!=1.28.1,>=1.24.0)
Requires-Dist: oslo.upgradecheck (>=0.1.0)
Requires-Dist: oslo.utils (>=3.33.0)
Requires-Dist: pbr (!=2.1.0,>=2.0.0)
Requires-Dist: pecan (!=1.0.2,!=1.0.3,!=1.0.4,!=1.2,>=1.0.0)
Requires-Dist: python-dateutil (>=2.5.3)
Requires-Dist: python-swiftclient (>=3.2.0)
Requires-Dist: setuptools (!=24.0.0,!=34.0.0,!=34.0.1,!=34.0.2,!=34.0.3,!=34.1.0,!=34.1.1,!=34.2.0,!=34.3.0,!=34.3.1,!=34.3.2,!=36.2.0,>=21.0.0)
Requires-Dist: sqlalchemy-migrate (>=0.11.0)
Requires-Dist: stevedore (>=1.20.0)
Requires-Dist: tenacity (>=4.4.0)
